bam_add_eof/__init__.py
bam_add_eof/__main__.py
bam_add_eof/main.py
bam_add_eof-0.3.dist-info/DESCRIPTION.rst
bam_add_eof-0.3.dist-info/METADATA
bam_add_eof-0.3.dist-info/RECORD
bam_add_eof-0.3.dist-info/WHEEL
bam_add_eof-0.3.dist-info/metadata.json
bam_add_eof-0.3.dist-info/top_level.txt
