Metadata-Version: 2.0
Name: bam-add-eof
Version: 0.3
Summary: if a BAM is missing EOF, add it, else output original BAM
Home-page: https://github.com/jeremiahsavage/bam_add_eof
Author: Jeremiah H. Savage
Author-email: jeremiahsavage@gmail.com
License: Apache 2.0
Platform: UNKNOWN
Classifier: Development Status :: 3 - Alpha
Classifier: Intended Audience :: Developers
Classifier: License :: OSI Approved :: Apache Software License
Classifier: Programming Language :: Python
Classifier: Programming Language :: Python :: 2
Classifier: Programming Language :: Python :: 3
Requires-Dist: cdis-pipe-utils
Requires-Dist: cython
Requires-Dist: pandas
Requires-Dist: pysam
Requires-Dist: sqlalchemy
